{
  "entity": {
    "binary_sensor": {
      "bubblesoak_support": {
        "default": "mdi:water-off",
        "state": {
          "on": "mdi:water"
        }
      },
      "child_lock": {
        "default": "mdi:lock-open",
        "state": {
          "on": "mdi:lock"
        }
      },
      "dryer_wrinkle_prevent_active": {
        "default": "mdi:tumble-dryer",
        "state": {
          "on": "mdi:tumble-dryer-alert"
        }
      },
      "remote_control": {
        "default": "mdi:remote-off",
        "state": {
          "on": "mdi:remote"
        }
      },
      "keep_fresh_mode": {
        "default": "mdi:creation"
      }
    },
    "button": {
      "estimate_operation_time": {
        "default": "mdi:clock-end"
      },
      "reset_water_filter": {
        "default": "mdi:reload"
      },
      "state_cancel": {
        "default": "mdi:stop-circle"
      },
      "state_pause_resume": {
        "default": "mdi:pause-circle"
      },
      "state_start": {
        "default": "mdi:play-circle"
      },
      "stop": {
        "default": "mdi:stop"
      }
    },
    "climate": {
      "air_conditioner": {
        "state_attributes": {
          "fan_mode": {
            "state": {
              "turbo": "mdi:wind-power"
            }
          },
          "preset_mode": {
            "state": {
              "long_wind": "mdi:weather-windy",
              "motion_direct": "mdi:account-arrow-left",
              "motion_indirect": "mdi:account-arrow-right",
              "quiet": "mdi:volume-off",
              "smart": "mdi:leaf",
              "wind_free": "mdi:weather-dust",
              "wind_free_sleep": "mdi:sleep"
            }
          }
        }
      }
    },
    "number": {
      "delay_time": {
        "default": "mdi:timer"
      },
      "freezer_temperature": {
        "default": "mdi:snowflake-thermometer"
      }
    },
    "select": {
      "auto_dispense_detergent_amount": {
        "default": "mdi:beaker"
      },
      "auto_dispense_detergent_density": {
        "default": "mdi:circle-opacity"
      },
      "auto_dispense_softener_amount": {
        "default": "mdi:beaker"
      },
      "auto_dispense_softener_density": {
        "default": "mdi:circle-opacity"
      },
      "dryer_dry_level": {
        "default": "mdi:waves-arrow-up"
      },
      "dryer_drying_temperature": {
        "default": "mdi:thermometer"
      },
      "dryer_drying_time": {
        "default": "mdi:clock-time-four"
      },
      "flexible_detergent_amount": {
        "default": "mdi:car-coolant-level"
      },
      "lamp": {
        "default": "mdi:lightbulb",
        "state": {
          "on": "mdi:lightbulb-on",
          "off": "mdi:lightbulb-off"
        }
      },
      "machine_state": {
        "default": "mdi:play-speed",
        "state": {
          "run": "mdi:play",
          "pause": "mdi:pause",
          "stop": "mdi:stop"
        }
      },
      "washer_rinse_cycles": {
        "default": "mdi:water-sync"
      },
      "washer_soil_level": {
        "default": "mdi:brightness-7"
      },
      "washer_spin_level": {
        "default": "mdi:autorenew"
      },
      "washer_water_temperature": {
        "default": "mdi:water-thermometer"
      }
    },
    "sensor": {
      "cooktop_operating_state": {
        "default": "mdi:stove",
        "state": {
          "ready": "mdi:play-speed",
          "run": "mdi:play",
          "paused": "mdi:pause",
          "finished": "mdi:food-turkey"
        }
      },
      "completion_time": {
        "default": "mdi:clock-end"
      },
      "diverter_valve_position": {
        "state": {
          "room": "mdi:sofa",
          "tank": "mdi:water-boiler"
        }
      },
      "heating_mode": {
        "state": {
          "off": "mdi:power",
          "manual": "mdi:cog",
          "boost": "mdi:flash",
          "keep_warm": "mdi:fire",
          "quick_preheat": "mdi:heat-wave",
          "defrost": "mdi:car-defrost-rear",
          "melt": "mdi:snowflake-melt",
          "simmer": "mdi:fire"
        }
      },
      "manual_level": {
        "default": "mdi:radiator",
        "state": {
          "0": "mdi:radiator-off"
        }
      },
      "operating_progress": {
        "default": "mdi:progress-clock"
      },
      "operating_state": {
        "default": "mdi:state-machine"
      },
      "operation_time": {
        "default": "mdi:clock"
      },
      "remaining_amount_dispense_detergent": {
        "default": "mdi:bottle-tonic-outline"
      },
      "remaining_amount_dispense_softener": {
        "default": "mdi:bottle-tonic-outline"
      },
      "remaining_time": {
        "default": "mdi:timelapse"
      }
    },
    "switch": {
      "auto_cycle_link": {
        "default": "mdi:link-off",
        "state": {
          "on": "mdi:link"
        }
      },
      "bubble_soak": {
        "default": "mdi:water-off",
        "state": {
          "on": "mdi:water"
        }
      },
      "display_lighting": {
        "default": "mdi:lightbulb",
        "state": {
          "off": "mdi:lightbulb-off",
          "on": "mdi:lightbulb-on"
        }
      },
      "ice_maker": {
        "default": "mdi:delete-variant"
      },
      "keep_fresh_mode": {
        "default": "mdi:creation"
      },
      "power_cool": {
        "default": "mdi:snowflake-alert"
      },
      "power_freeze": {
        "default": "mdi:snowflake"
      },
      "sanitize": {
        "default": "mdi:lotion"
      },
      "sound_effect": {
        "default": "mdi:volume-high",
        "state": {
          "off": "mdi:volume-off",
          "on": "mdi:volume-high"
        }
      },
      "wrinkle_prevent": {
        "default": "mdi:tumble-dryer",
        "state": {
          "off": "mdi:tumble-dryer-off"
        }
      }
    }
  }
}
